unikold.connector-2.0-py2.7-nspkg.pth
unikold/connector/__init__.py
unikold/connector/configure.zcml
unikold/connector/interfaces.py
unikold/connector/ldap.py
unikold/connector/lsf.py
unikold/connector/permissions.zcml
unikold/connector/setuphandlers.py
unikold/connector/soap.py
unikold/connector/testing.py
unikold/connector/upgrades.py
unikold/connector/upgrades.zcml
unikold/connector/utils.py
unikold/connector/utils_lsf.py
unikold/connector/utils_sentry.py
unikold/connector/xml.py
unikold/connector/browser/__init__.py
unikold/connector/browser/configure.zcml
unikold/connector/browser/controlpanel.py
unikold/connector/browser/controlpanel_ldap.py
unikold/connector/browser/controlpanel_lsf.py
unikold/connector/browser/forms.py
unikold/connector/browser/views.py
unikold/connector/browser/overrides/.gitkeep
unikold/connector/browser/static/.gitkeep
unikold/connector/browser/templates/ldap_search_query_view.pt
unikold/connector/browser/templates/soap_query_view.pt
unikold/connector/browser/templates/soap_test_view.pt
unikold/connector/browser/templates/update_all_view.pt
unikold/connector/browser/templates/xml_query_view.pt
unikold/connector/content/__init__.py
unikold/connector/content/ldap_search_query.py
unikold/connector/content/lsf_query.py
unikold/connector/content/lsf_search_query.py
unikold/connector/content/soap_queries_folder.xml
unikold/connector/content/soap_query.py
unikold/connector/content/xml_query.py
unikold/connector/content/xml_query.xml
unikold/connector/locales/README.rst
unikold/connector/locales/__init__.py
unikold/connector/locales/unikold.connector.pot
unikold/connector/locales/update.py
unikold/connector/locales/update.sh
unikold/connector/locales/de/LC_MESSAGES/unikold.connector.mo
unikold/connector/locales/de/LC_MESSAGES/unikold.connector.po
unikold/connector/locales/en/LC_MESSAGES/unikold.connector.mo
unikold/connector/locales/en/LC_MESSAGES/unikold.connector.po
unikold/connector/profiles/default/browserlayer.xml
unikold.connector-2.0.dist-info/LICENSE.GPL
unikold.connector-2.0.dist-info/LICENSE.rst
unikold.connector-2.0.dist-info/METADATA
unikold.connector-2.0.dist-info/WHEEL
unikold.connector-2.0.dist-info/entry_points.txt
unikold.connector-2.0.dist-info/namespace_packages.txt
unikold.connector-2.0.dist-info/top_level.txt
unikold.connector-2.0.dist-info/RECORD
