Metadata-Version: 2.1
Name: unikold.connector
Version: 2.0
Summary: Plone addon for making persistent SOAP requests
Home-page: https://github.com/mbarde/unikold.connector
Author: Matthias Barde
Author-email: mbarde@uni-koblenz.de
License: GPL version 2
Download-URL: https://github.com/mbarde/unikold.connector/archive/refs/tags/v2.0.tar.gz
Keywords: Python Plone
Platform: UNKNOWN
Classifier: Development Status :: 5 - Production/Stable
Classifier: Intended Audience :: Developers
Classifier: Environment :: Web Environment
Classifier: Framework :: Plone
Classifier: Framework :: Plone :: 5.0
Classifier: Framework :: Plone :: 5.1
Classifier: Framework :: Plone :: 5.2
Classifier: Programming Language :: Python :: 3
Classifier: Programming Language :: Python :: 3.7
Classifier: Operating System :: OS Independent
Classifier: License :: OSI Approved :: GNU General Public License v2 (GPLv2)
Requires-Dist: plone.app.dexterity
Requires-Dist: plone.api (>=1.8.4)
Requires-Dist: Products.GenericSetup (>=1.8.2)
Requires-Dist: setuptools
Requires-Dist: z3c.jbot
Requires-Dist: zeep (>=4.0.0)
Requires-Dist: python-ldap
Provides-Extra: test
Requires-Dist: plone.app.testing ; extra == 'test'
Requires-Dist: plone.testing (>=5.0.0) ; extra == 'test'
Requires-Dist: plone.app.contenttypes ; extra == 'test'
Requires-Dist: plone.app.robotframework[debug] ; extra == 'test'
